{
    "lambda_name": "cookiecutter_lambda",
    "short_description": "This is a description of my awesome lambda function",
    "open_source_license": [
        "MIT",
        "BSD",
        "GPLv3",
        "Apache Software License 2.0",
        "Not open source"
    ],
    "runtime": [
        "python:3.6",
        "python:3.8",
        "python:3.9"
    ],
    "handler_file": "lambda_function.py",
    "version": "0.1.0",
    "create_lambda_layer": ["Yes", "No"],
    "create_local_virtualenv": ["Yes", "No"],
    "cicd_github_action": ["Yes", "No"],
    "git_init": ["Yes", "No"],
    "auto_lambda_creation": ["Yes", "No"],
    "author": "",
    "email": "",
    "organization": ""
}